mpfi/__init__.py
mpfi/config_default.py
mpfi/constants.py
mpfi/export_data.py
mpfi/load_data.py
mpfi/util.py
mpfi-0.0.27.dist-info/LICENSE
mpfi-0.0.27.dist-info/METADATA
mpfi-0.0.27.dist-info/WHEEL
mpfi-0.0.27.dist-info/top_level.txt
mpfi-0.0.27.dist-info/RECORD
