Metadata-Version: 2.2
Name: mpfi
Version: 0.0.27
Summary: FIS Prophet Model Point File Inspector and Processor
Home-page: https://github.com/bensonby/mpfi
Author: Benson Yeung
Author-email: bensonby@gmail.com
Classifier: Programming Language :: Python :: 3
Classifier: License :: OSI Approved :: MIT License
Classifier: Operating System :: OS Independent
Requires-Python: >=3.6
License-File: LICENSE
Requires-Dist: pandas>=1.5.0
Dynamic: author
Dynamic: author-email
Dynamic: classifier
Dynamic: description
Dynamic: description-content-type
Dynamic: home-page
Dynamic: requires-dist
Dynamic: requires-python
Dynamic: summary
